allproxy/Get.py
allproxy/Send.py
allproxy/__init__.py
allproxy/testing.py
allproxy-1.6.dist-info/LICENSE.txt
allproxy-1.6.dist-info/METADATA
allproxy-1.6.dist-info/WHEEL
allproxy-1.6.dist-info/top_level.txt
allproxy-1.6.dist-info/RECORD
